dawg.so
DAWG-0.7.8.dist-info/DESCRIPTION.rst
DAWG-0.7.8.dist-info/METADATA
DAWG-0.7.8.dist-info/metadata.json
DAWG-0.7.8.dist-info/RECORD
DAWG-0.7.8.dist-info/top_level.txt
DAWG-0.7.8.dist-info/WHEEL
